yaghm/__init__.py
yaghm/custom_command.py
yaghm/disable.py
yaghm/enable.py
yaghm/lib.py
yaghm/list_hooks.py
yaghm/main.py
yaghm/templates/wrapper.jinja2
yaghm-0.3.1.dist-info/LICENSE
yaghm-0.3.1.dist-info/METADATA
yaghm-0.3.1.dist-info/WHEEL
yaghm-0.3.1.dist-info/entry_points.txt
yaghm-0.3.1.dist-info/top_level.txt
yaghm-0.3.1.dist-info/RECORD
