Metadata-Version: 2.1
Name: yaghm
Version: 0.3.1
Summary: Minimal git hook manager for the command line.
Home-page: https://www.github.com/metov/yaghm
Author: Azat Akhmetov
Author-email: azatinfo@yandex.com
Classifier: Programming Language :: Python :: 3
Classifier: Development Status :: 3 - Alpha
Classifier: License :: OSI Approved :: MIT License
License-File: LICENSE
Requires-Dist: coloredlogs
Requires-Dist: docopt
Requires-Dist: GitPython
Requires-Dist: Jinja2
Requires-Dist: PyYAML
Requires-Dist: questionary
Requires-Dist: ruamel.yaml
